datetime_utils/__init__.py
datetime_utils/core.py
tests/__init__.py
tests/test_core.py
datetime_utils_sribandi-0.1.dist-info/METADATA
datetime_utils_sribandi-0.1.dist-info/WHEEL
datetime_utils_sribandi-0.1.dist-info/top_level.txt
datetime_utils_sribandi-0.1.dist-info/RECORD
